{"cameraMode":{"drawMode":0,"name":"Shaded","section":"Shading Mode"},"sceneLighting":true,"audioPlay":false,"sceneViewState":{"m_AlwaysRefresh":false,"showFog":true,"showSkybox":false,"showFlares":true,"showImageEffects":true,"showParticleSystems":true,"showVisualEffectGraphs":true,"m_FxEnabled":true},"in2DMode":false,"pivot":{"x":0.0,"y":0.0,"z":0.0024995803833007814},"rotation":{"x":0.26411786675453188,"y":0.011872993782162667,"z":-0.0032516124192625286,"w":0.9644129872322083},"size":17.861888885498048,"orthographic":false}